onet/__init__.py
onet/__main__.py
onet-0.1.0.dist-info/LICENSE.txt
onet-0.1.0.dist-info/METADATA
onet-0.1.0.dist-info/WHEEL
onet-0.1.0.dist-info/entry_points.txt
onet-0.1.0.dist-info/top_level.txt
onet-0.1.0.dist-info/RECORD
